akantu_geomechanical_solver/__init__.py
akantu_geomechanical_solver/akantu_geomechanical_solver.py
akantu_geomechanical_solver-0.3.0.dist-info/LICENSE
akantu_geomechanical_solver-0.3.0.dist-info/METADATA
akantu_geomechanical_solver-0.3.0.dist-info/WHEEL
akantu_geomechanical_solver-0.3.0.dist-info/RECORD
