Metadata-Version: 2.1
Name: akantu-geomechanical-solver
Version: 0.3.0
Summary: Geomechanical simulator based on the open-source FEM library Akantu.
Home-page: https://gitlab.com/emil.gallyamov/akantu-geomechanical-solver
License: GPL
Author: Emil Gallyamov
Author-email: emil.gallyamov@epfl.ch
Requires-Python: >=3.10,<4.0
Classifier: License :: Other/Proprietary License
Classifier: Programming Language :: Python :: 3
Classifier: Programming Language :: Python :: 3.10
Classifier: Programming Language :: Python :: 3.11
Classifier: Programming Language :: Python :: 3.12
Classifier: Programming Language :: Python :: 3.13
Provides-Extra: dev
Provides-Extra: doc
Provides-Extra: parallel
Provides-Extra: serial
Provides-Extra: test
Requires-Dist: akantu (==4.0.1rc2+226.gad188433212) ; extra == "serial"
Requires-Dist: gmsh (>=4.13.1,<5.0.0)
Requires-Dist: mpi4py (>=4.0.0,<5.0.0)
Requires-Dist: mpmath (>=1.3.0,<2.0.0) ; extra == "dev" or extra == "test"
Requires-Dist: numpy (>=2.0.0,<3.0.0)
Requires-Dist: pre-commit (>=3.8.0,<4.0.0) ; extra == "dev"
Requires-Dist: pytest (>=8.3.2,<9.0.0) ; extra == "dev" or extra == "test"
Requires-Dist: scipy (>=1.14.0,<2.0.0) ; extra == "dev" or extra == "test" or extra == "parallel"
Requires-Dist: sphinx (>=8.0.2,<9.0.0) ; extra == "doc" or extra == "dev"
Project-URL: Repository, https://gitlab.com/emil.gallyamov/akantu-geomechanical-solver
